sphinx_table-1.2.1-py3.9-nspkg.pth
sphinxcontrib/table/__init__.py
sphinxcontrib/table/cell.py
sphinxcontrib/table/coordinate.py
sphinxcontrib/table/excel.py
sphinxcontrib/table/span.py
sphinxcontrib/table/table.py
sphinx_table-1.2.1.dist-info/LICENSE
sphinx_table-1.2.1.dist-info/METADATA
sphinx_table-1.2.1.dist-info/WHEEL
sphinx_table-1.2.1.dist-info/namespace_packages.txt
sphinx_table-1.2.1.dist-info/top_level.txt
sphinx_table-1.2.1.dist-info/RECORD
